{"nodes": [{"id": "respond_node", "label": "respond builds text and persists session", "source_file": "agent/nodes/respond.py"}], "edges": [{"source": "respond_node", "target": "document_store_ops", "relation": "persists_session_document_via_store_session", "confidence": "EXTRACTED", "confidence_score": 1.0, "source_file": "agent/nodes/respond.py"}, {"source": "respond_node", "target": "document_store_ops", "relation": "increments_usage_when_existing_skill_matched", "confidence": "EXTRACTED", "confidence_score": 1.0, "source_file": "agent/nodes/respond.py"}, {"source": "respond_node", "target": "medimind_state", "relation": "reads_state_to_build_response_text", "confidence": "EXTRACTED", "confidence_score": 1.0, "source_file": "agent/nodes/respond.py"}, {"source": "respond_node", "target": "session_model", "relation": "session_payload_matches_session_schema_shape", "confidence": "INFERRED", "confidence_score": 0.72, "source_file": "agent/nodes/respond.py"}], "hyperedges": []}